sciops/__init__.py
sciops-0.1.1.dist-info/WHEEL
sciops-0.1.1.dist-info/METADATA
sciops-0.1.1.dist-info/RECORD
